{"adventure":{"id":1050,"campaignId":27,"name":"Tall Tales","freeplay":1054,"locationId":2},"variants":[{"id":1051,"name":"Nightmare Rats!","requirements":{"ids":[1050]},"base":{"area":200,"rewards":[{"reward":"red_rubies","amount":400}]},"patrons":[{"id":1,"area":300},{"id":2,"area":325},{"id":3,"area":350},{"id":4,"area":375},{"id":5,"area":825}]},{"id":1052,"name":"An Unexpected Geist","requirements":{"ids":[1050],"count":{"count":4,"campaign":27}},"base":{"area":250,"rewards":[{"reward":"red_rubies","amount":500}]},"patrons":[{"id":1,"area":350},{"id":2,"area":375},{"id":3,"area":400},{"id":4,"area":425},{"id":5,"area":825}]},{"id":1053,"name":"Back to Nature","requirements":{"ids":[1050],"count":{"count":13,"campaign":27}},"base":{"area":300,"rewards":[{"reward":"red_rubies","amount":600}]},"patrons":[{"id":1,"area":400},{"id":2,"area":425},{"id":3,"area":450},{"id":4,"area":475},{"id":5,"area":825}]}],"areas":[{"id":7202,"questId":7066,"bgId":479,"time":"night","monsters":[10,11,12]},{"id":7203,"questId":7067,"bgId":479,"time":"night","monsters":[10,11,12]},{"id":7204,"questId":7068,"bgId":479,"time":"night","monsters":[135,136,137,90,92,91]},{"id":7205,"questId":7069,"bgId":479,"time":"night","monsters":[10,11,12,90,92,91]},{"id":7206,"questId":7070,"bgId":479,"time":"night","waves":[[91,90,90,90,90],[90,92,92,91,91],[93]]},{"id":7207,"questId":7071,"bgId":336,"monsters":[46,47,48]},{"id":7208,"questId":7072,"bgId":336,"monsters":[46,47,48]},{"id":7209,"questId":7073,"bgId":336,"monsters":[46,47,48,765,766,767]},{"id":7210,"questId":7074,"bgId":337,"monsters":[46,47,48,765,766,767]},{"id":7211,"questId":7075,"bgId":337,"waves":[[48,48,47,47,46],[46,47,48,46,47],[1573]]},{"id":7212,"questId":7076,"bgId":479,"time":"night","monsters":[90,92,91,135,136,137]},{"id":7213,"questId":7077,"bgId":479,"time":"night","monsters":[90,92,91,135,136,137]},{"id":7214,"questId":7078,"bgId":479,"time":"night","monsters":[90,92,91,135,136,137]},{"id":7215,"questId":7079,"bgId":479,"time":"night","monsters":[90,92,91,135,136,137]},{"id":7216,"questId":7080,"bgId":479,"time":"night","waves":[[136,136,90,92,91],[90,135,91,136,90],[930]]},{"id":7217,"questId":7081,"bgId":479,"time":"night","monsters":[90,92,91,135,136,137]},{"id":7218,"questId":7082,"bgId":121,"monsters":[181,182,183,282,283,284]},{"id":7219,"questId":7083,"bgId":121,"monsters":[282,283,284,46,47,48]},{"id":7220,"questId":7084,"bgId":128,"monsters":[282,283,284,181,182,183]},{"id":7221,"questId":7085,"bgId":128,"spawner":true,"staticMonsters":[1531],"monsters":[282,283,284]},{"id":7222,"questId":7086,"bgId":479,"time":"night","monsters":[90,92,91]},{"id":7223,"questId":7087,"bgId":479,"time":"night","monsters":[90,92,91,135,136,137]},{"id":7224,"questId":7088,"bgId":479,"time":"night","monsters":[135,136,137]},{"id":7225,"questId":7089,"bgId":479,"time":"night","monsters":[135,136,137]},{"id":7226,"questId":7090,"bgId":479,"time":"night","waves":[[137,91,136,136,137],[137,137,90,136,137],[515]]},{"id":7227,"questId":7091,"bgId":479,"time":"night","monsters":[90,92,91]},{"id":7228,"questId":7092,"bgId":479,"time":"night","monsters":[90,92,91]},{"id":7229,"questId":7093,"bgId":286,"monsters":[447,448,449,46,47,48]},{"id":7230,"questId":7094,"bgId":286,"monsters":[447,448,449,302,303,304]},{"id":7231,"questId":7095,"bgId":287,"waves":[[299,298,298,297,297],[299,299,298,298,297],[686]]},{"id":7232,"questId":7096,"bgId":479,"time":"night","monsters":[90,92,91,135,136,137]},{"id":7233,"questId":7097,"bgId":479,"time":"night","monsters":[90,92,91,135,136,137]},{"id":7234,"questId":7098,"bgId":751,"monsters":[1525,1526,1527]},{"id":7235,"questId":7099,"bgId":751,"monsters":[1525,1526,1527,46,47,48]},{"id":7236,"questId":7100,"bgId":751,"waves":[[1527,1527,1525,1525,1526],[1526,1525,1527,1527,1526],[1524]]},{"id":7237,"questId":7101,"bgId":479,"time":"night","monsters":[90,92,91,135,136,137]},{"id":7238,"questId":7102,"bgId":479,"time":"night","monsters":[90,92,91,135,136,137]},{"id":7239,"questId":7103,"bgId":146,"monsters":[635,636,637,46,47,48]},{"id":7240,"questId":7104,"bgId":146,"monsters":[46,47,48]},{"id":7241,"questId":7105,"bgId":146,"waves":[[636,636,637,637,637],[635,636,635,635,637],[1530]]},{"id":7242,"questId":7106,"bgId":752,"monsters":[46,47,48]},{"id":7243,"questId":7107,"bgId":752,"monsters":[46,47,48,1552,1551,1550]},{"id":7244,"questId":7108,"bgId":752,"monsters":[1552,1551,1550]},{"id":7245,"questId":7109,"bgId":753,"monsters":[1552,1551,1550,46,47,48]},{"id":7246,"questId":7110,"bgId":753,"waves":[[1552,1552,1552,1551,1551],[1550,1551,1551,1551,1550],[49]]},{"id":7247,"questId":7111,"bgId":479,"time":"night","monsters":[90,92,91,135,136,137]},{"id":7248,"questId":7112,"bgId":479,"time":"night","monsters":[90,92,91,135,136,137]},{"id":7249,"questId":7113,"bgId":479,"time":"night","monsters":[8,9]},{"id":7250,"questId":7114,"bgId":479,"time":"night","monsters":[90,92,91,135,136,137]},{"id":7251,"questId":7115,"bgId":479,"time":"night","waves":[[136,90,135,91,90],[135,91,90,135,92],[1528]]}],"backgrounds":[{"id":479,"distractions":[9,9],"tags":["outdoors"],"isFixed":true},{"id":336,"distractions":[18],"tags":["outdoors"],"isFixed":true},{"id":337,"distractions":[18],"tags":["outdoors"],"isFixed":true},{"id":121,"distractions":[10,18,11,11],"tags":["outdoors"]},{"id":128,"distractions":[18,12,14,16],"tags":["outdoors"]},{"id":286,"distractions":[],"tags":["underground"],"isFixed":true},{"id":287,"distractions":[],"tags":["underground"],"isFixed":true},{"id":751,"distractions":[9],"isFixed":true},{"id":146,"distractions":[13,12],"tags":["outdoors"]},{"id":752,"distractions":[]},{"id":753,"distractions":[],"isFixed":true}],"monsters":[{"id":9,"name":"Rabbit","tags":["beast","melee"],"type":1},{"id":91,"name":"Pixie","tags":["fey","ranged","flying"],"type":1},{"id":137,"name":"Sprite","tags":["fey","melee","flying"],"type":1},{"id":10,"name":"Wolf","tags":["beast","melee"],"type":1},{"id":11,"name":"Wolf","tags":["beast","melee"],"type":1},{"id":12,"name":"Wolf","tags":["beast","melee"],"type":1},{"id":135,"name":"Sprite","tags":["fey","melee","flying"],"type":1},{"id":136,"name":"Sprite","tags":["fey","melee","flying"],"type":1},{"id":90,"name":"Pixie","tags":["fey","ranged","flying"],"type":1},{"id":92,"name":"Pixie","tags":["fey","ranged","flying"],"type":1},{"id":93,"name":"Pixie Leader","tags":["fey","melee","boss"],"type":2,"damageModifier":2.5,"healthModifier":50},{"id":46,"name":"Giant Rat","tags":["beast","melee"],"type":1},{"id":47,"name":"Giant Rat","tags":["beast","melee"],"type":1},{"id":48,"name":"Giant Rat","tags":["beast","melee"],"type":1},{"id":765,"name":"Black Cat","tags":["beast","melee"],"type":1},{"id":766,"name":"Black Cat","tags":["beast","melee"],"type":1},{"id":767,"name":"Black Cat","tags":["beast","melee"],"type":1},{"id":1573,"name":"Kingsport's Gelatinous Cube","tags":["boss","ooze","melee","beast","hits_based"],"type":2,"damageModifier":2.5,"healthModifier":4},{"id":930,"name":"Pixie Riding an Intellect Devourer","tags":["fey","melee","aberration"],"type":1,"healthModifier":25},{"id":181,"name":"Flying Snake","tags":["beast","melee","flying"],"type":1},{"id":182,"name":"Flying Snake","tags":["beast","melee","flying"],"type":1},{"id":183,"name":"Flying Snake","tags":["beast","melee","flying"],"type":1},{"id":282,"name":"Flying Monkey","tags":["beast","melee","flying"],"type":1},{"id":283,"name":"Flying Monkey","tags":["beast","melee","flying"],"type":1},{"id":284,"name":"Flying Monkey","tags":["beast","melee","flying"],"type":1},{"id":1531,"name":"King of Feathers","tags":["beast","boss","ranged","hits_based","dinosaur"],"type":2,"damageModifier":2.5,"healthModifier":50},{"id":515,"name":"Pixie Riding a Crocodile","tags":["boss","beast","fey","melee"],"type":2,"damageModifier":2.5,"healthModifier":50},{"id":447,"name":"Velociraptor","tags":["beast","melee","dinosaur"],"type":1},{"id":448,"name":"Velociraptor","tags":["beast","melee","dinosaur"],"type":1},{"id":449,"name":"Velociraptor","tags":["beast","melee","dinosaur"],"type":1},{"id":302,"name":"Triceratops","tags":["beast","melee","dinosaur"],"type":1},{"id":303,"name":"Triceratops","tags":["beast","melee","dinosaur"],"type":1},{"id":304,"name":"Triceratops","tags":["beast","dinosaur","melee"],"type":1},{"id":299,"name":"Stegosaurus","tags":["melee","beast","dinosaur"],"type":1},{"id":298,"name":"Stegosaurus","tags":["melee","beast","dinosaur"],"type":1},{"id":297,"name":"Stegosaurus","tags":["beast","melee","dinosaur"],"type":1},{"id":686,"name":"Acererak","tags":["ranged","undead","boss","armor_based","flying"],"type":2,"damageModifier":2.5,"healthModifier":50},{"id":1525,"name":"Clown Gazer","tags":["ranged","aberration"],"type":1},{"id":1526,"name":"Clown Gazer","tags":["ranged","aberration"],"type":1},{"id":1527,"name":"Clown Gazer","tags":["ranged","aberration"],"type":1},{"id":1524,"name":"Xanathar Clown","tags":["boss","aberration","armor_based","ranged","flying"],"type":2,"damageModifier":2.5,"healthModifier":50},{"id":635,"name":"Monodrone","tags":["construct","melee","modron"],"type":1},{"id":636,"name":"Monodrone","tags":["construct","melee","modron"],"type":1},{"id":637,"name":"Monodrone","tags":["construct","melee","modron"],"type":1},{"id":1530,"name":"Angry Goat","tags":["boss","melee","beast"],"type":2,"damageModifier":2.5},{"id":1552,"name":"Gremishka","tags":["melee","monstrosity"],"type":1},{"id":1551,"name":"Gremishka","tags":["melee","monstrosity"],"type":1},{"id":1550,"name":"Gremishka","tags":["melee","monstrosity"],"type":1},{"id":49,"name":"Drunk Wizard","tags":["human","humanoid","ranged","boss"],"type":2,"damageModifier":2.5,"healthModifier":50},{"id":8,"name":"Rabbit","tags":["beast","melee"],"type":1},{"id":1528,"name":"Pixie Riding a Displacer Kitten","tags":["boss","melee","fey","monstrosity"],"type":2,"damageModifier":2.5}],"quests":[{"id":7066,"type":2,"goal":25,"desc":"Enemies"},{"id":7067,"type":2,"goal":25,"desc":"Enemies"},{"id":7068,"type":1,"goal":25,"desc":"Carnival Advertisements"},{"id":7069,"type":2,"goal":25,"desc":"Enemies"},{"id":7070,"type":3,"goal":1,"desc":"Pixie Leader"},{"id":7071,"type":2,"goal":25,"desc":"Enemies"},{"id":7072,"type":2,"goal":25,"desc":"Enemies"},{"id":7073,"type":1,"goal":25,"desc":"Coin Pouches"},{"id":7074,"type":2,"goal":25,"desc":"Enemies"},{"id":7075,"type":3,"goal":1,"desc":"Gelatinous Cube"},{"id":7076,"type":2,"goal":25,"desc":"Enemies"},{"id":7077,"type":2,"goal":25,"desc":"Enemies"},{"id":7078,"type":1,"goal":25,"desc":"Berries"},{"id":7079,"type":2,"goal":25,"desc":"Enemies"},{"id":7080,"type":3,"goal":1,"desc":"Pixie Leader"},{"id":7081,"type":1,"goal":25,"desc":"Big Rocks"},{"id":7082,"type":2,"goal":25,"desc":"Enemies"},{"id":7083,"type":1,"goal":25,"desc":"Monkey Hats"},{"id":7084,"type":2,"goal":25,"desc":"Enemies"},{"id":7085,"type":3,"goal":1,"desc":"King of Feathers"},{"id":7086,"type":2,"goal":25,"desc":"Enemies"},{"id":7087,"type":2,"goal":25,"desc":"Enemies"},{"id":7088,"type":1,"goal":25,"desc":"Witchlight Vane Toys"},{"id":7089,"type":2,"goal":25,"desc":"Enemies"},{"id":7090,"type":3,"goal":1,"desc":"Pixie Leader"},{"id":7091,"type":2,"goal":25,"desc":"Enemies"},{"id":7092,"type":2,"goal":25,"desc":"Enemies"},{"id":7093,"type":1,"goal":25,"desc":"Soul Coins"},{"id":7094,"type":2,"goal":25,"desc":"Enemies"},{"id":7095,"type":3,"goal":1,"desc":"Acererak"},{"id":7096,"type":2,"goal":25,"desc":"Enemies"},{"id":7097,"type":1,"goal":10,"desc":"Big Branches"},{"id":7098,"type":2,"goal":25,"desc":"Enemies"},{"id":7099,"type":2,"goal":25,"desc":"Enemies"},{"id":7100,"type":3,"goal":1,"desc":"Xanathar Clown"},{"id":7101,"type":2,"goal":25,"desc":"Enemies"},{"id":7102,"type":2,"goal":25,"desc":"Enemies"},{"id":7103,"type":1,"goal":25,"desc":"Modron Pieces"},{"id":7104,"type":2,"goal":25,"desc":"Enemies"},{"id":7105,"type":3,"goal":1,"desc":"Goat"},{"id":7106,"type":2,"goal":25,"desc":"Enemies"},{"id":7107,"type":2,"goal":25,"desc":"Enemies"},{"id":7108,"type":1,"goal":25,"desc":"Priceless Artifacts"},{"id":7109,"type":2,"goal":25,"desc":"Enemies"},{"id":7110,"type":3,"goal":1,"desc":"Drunk Wizard"},{"id":7111,"type":2,"goal":25,"desc":"Enemies"},{"id":7112,"type":2,"goal":25,"desc":"Enemies"},{"id":7113,"type":1,"goal":25,"desc":"Rabbit Carcasses"},{"id":7114,"type":2,"goal":25,"desc":"Enemies"},{"id":7115,"type":3,"goal":1,"desc":"Pixie Leader"}],"distractions":[{"id":9,"name":"Bat (Flying)","isBush":false},{"id":18,"name":"Seagull (Flying)","isBush":false},{"id":10,"name":"Crab (Scurrying)","isBush":false},{"id":11,"name":"Crate","isBush":false},{"id":12,"name":"Bug (Scurrying)","isBush":false},{"id":14,"name":"Spider Drop","isBush":false},{"id":16,"name":"Snake","isBush":false},{"id":13,"name":"Rat (Scurrying)","isBush":false}]}