{"adventure":{"id":1330,"campaignId":27,"name":"Love Unsoiled","freeplay":1334,"locationId":72},"variants":[{"id":1331,"name":"The Play's the Thing!","requirements":{"ids":[1330]},"base":{"area":850,"rewards":[{"reward":"red_rubies","amount":1700}]},"patrons":[{"id":1,"area":950},{"id":2,"area":975},{"id":3,"area":1000},{"id":4,"area":1025},{"id":5,"area":1150}]},{"id":1332,"name":"All The World's A Stage","requirements":{"ids":[1330],"count":{"count":41,"campaign":27}},"base":{"area":900,"rewards":[{"reward":"red_rubies","amount":1800}]},"patrons":[{"id":1,"area":1000},{"id":2,"area":1025},{"id":3,"area":1050},{"id":4,"area":1075},{"id":5,"area":1200}]},{"id":1333,"name":"To Be or Not To Be","requirements":{"ids":[1330]},"base":{"area":950,"rewards":[{"reward":"red_rubies","amount":1900}]},"patrons":[{"id":1,"area":1050},{"id":2,"area":1075},{"id":3,"area":1100},{"id":4,"area":1125},{"id":5,"area":1250}]}],"areas":[{"id":8861,"questId":8726,"bgId":929,"monsters":[251,252,253]},{"id":8862,"questId":8727,"bgId":926,"monsters":[251,252,253]},{"id":8863,"questId":8728,"bgId":926,"monsters":[251,252,253,65,66,67]},{"id":8864,"questId":8729,"bgId":926,"monsters":[65,66,67]},{"id":8865,"questId":8730,"bgId":926,"waves":[[65,65,66,65,65],[67,65,65,65,67],[89]]},{"id":8866,"questId":8731,"bgId":930,"monsters":[46,47,48]},{"id":8867,"questId":8732,"bgId":930,"monsters":[46,47,48,925,926,927]},{"id":8868,"questId":8733,"bgId":930,"monsters":[925,926,927]},{"id":8869,"questId":8734,"bgId":930,"monsters":[925,926,927]},{"id":8870,"questId":8735,"bgId":930,"waves":[[926,925,927,925,926],[925,927,927,926,926],[271]]},{"id":8871,"questId":8736,"bgId":931,"monsters":[69,70,71]},{"id":8872,"questId":8737,"bgId":931,"monsters":[1864,1865,1866]},{"id":8873,"questId":8738,"bgId":931,"monsters":[1864,1865,1866]},{"id":8874,"questId":8739,"bgId":931,"monsters":[1864,1865,1866,69,70,71]},{"id":8875,"questId":8740,"bgId":931,"waves":[[71,70,71,71,70],[71,71,71,69,70],[1448]]},{"id":8876,"questId":8741,"bgId":932,"monsters":[122,123,124]},{"id":8877,"questId":8742,"bgId":932,"monsters":[428,429,430]},{"id":8878,"questId":8743,"bgId":932,"monsters":[428,429,430]},{"id":8879,"questId":8744,"bgId":932,"monsters":[428,429,430,122,123,124]},{"id":8880,"questId":8745,"bgId":932,"waves":[[1053,122,1052,1052,124],[1053,124,1052,124,1051],[1093]]},{"id":8881,"questId":8746,"bgId":931,"monsters":[1622,1621,1620]},{"id":8882,"questId":8747,"bgId":931,"monsters":[1622,1621,1620,1634,1633,1632]},{"id":8883,"questId":8748,"bgId":931,"monsters":[1622,1621,1620]},{"id":8884,"questId":8749,"bgId":931,"monsters":[1634,1633,1632,148,149,150,184]},{"id":8885,"questId":8750,"bgId":931,"waves":[[149,184,148,184,184],[149,148,150,149,148],[829]]},{"id":8886,"questId":8751,"bgId":933,"monsters":[1864,1865,1866]},{"id":8887,"questId":8752,"bgId":933,"monsters":[1864,1865,1866]},{"id":8888,"questId":8753,"bgId":933,"monsters":[1854,1855,1856,1864,1865,1866]},{"id":8889,"questId":8754,"bgId":933,"monsters":[1864,1865,1866,148,149,150,184]},{"id":8890,"questId":8755,"bgId":933,"waves":[[148,148,149,1855,148],[149,1856,149,1856,148],[1752]]},{"id":8891,"questId":8756,"bgId":934,"monsters":[1769,1770,1771,1854,1855,1856]},{"id":8892,"questId":8757,"bgId":934,"monsters":[1769,1770,1771,1854,1855,1856]},{"id":8893,"questId":8758,"bgId":934,"monsters":[1769,1770,1771,1082,1081]},{"id":8894,"questId":8759,"bgId":934,"monsters":[1488,1489,1490]},{"id":8895,"questId":8760,"bgId":934,"staticMonsters":[1558],"waves":[[1489,1488,1490,1489,1489],[1490,1489,1489,1488,1490]]},{"id":8896,"questId":8761,"bgId":935,"monsters":[61,62,63,255,256,257]},{"id":8897,"questId":8762,"bgId":935,"monsters":[80,81,82,255,256,257]},{"id":8898,"questId":8763,"bgId":935,"monsters":[242,243,244,231,232,233]},{"id":8899,"questId":8764,"bgId":935,"monsters":[255,256,257,176,177,178]},{"id":8900,"questId":8765,"bgId":935,"waves":[[177,178,177,255,176],[257,255,256,255,178],[162]]},{"id":8901,"questId":8766,"bgId":936,"monsters":[255,256,257]},{"id":8902,"questId":8767,"bgId":936,"monsters":[1857,1858,1859]},{"id":8903,"questId":8768,"bgId":936,"monsters":[1857,1858,1859]},{"id":8904,"questId":8769,"bgId":936,"monsters":[1857,1858,1859,1860,1861,1862]},{"id":8905,"questId":8770,"bgId":936,"waves":[[1861,1859,1859,1857,1862],[1861,1860,1860,1861,1860],[1614]]},{"id":8906,"questId":8771,"bgId":937,"monsters":[946,947,948,949,950,951]},{"id":8907,"questId":8772,"bgId":937,"monsters":[946,947,948,949,950,951]},{"id":8908,"questId":8773,"bgId":937,"monsters":[73,74,75]},{"id":8909,"questId":8774,"bgId":937,"monsters":[73,74,75,946,947,948]},{"id":8910,"questId":8775,"bgId":937,"waves":[[949,950,73,74,951],[75,949,74,73,950],[1863]]}],"backgrounds":[{"id":929,"distractions":[9,9],"tags":["underground"],"isFixed":true},{"id":926,"distractions":[],"tags":["underground"]},{"id":930,"distractions":[13,13,12],"tags":["underground"],"isFixed":true},{"id":931,"distractions":[13,12],"isFixed":true},{"id":932,"distractions":[12,12],"isFixed":true},{"id":933,"distractions":[13,13],"isFixed":true},{"id":934,"distractions":[18,18],"tags":["outdoors"],"isFixed":true},{"id":935,"distractions":[18],"tags":["outdoors"],"isFixed":true},{"id":936,"distractions":[18,18],"tags":["outdoors"],"isFixed":true},{"id":937,"distractions":[18],"tags":["outdoors"],"isFixed":true}],"monsters":[{"id":74,"name":"Satyr","tags":["fey","melee"],"type":1},{"id":926,"name":"Spider Hatchlings","tags":["melee","beast"],"type":1},{"id":251,"name":"Bat","tags":["beast","melee","flying"],"type":1},{"id":252,"name":"Bat","tags":["beast","melee","flying"],"type":1},{"id":253,"name":"Bat","tags":["beast","melee","flying"],"type":1},{"id":65,"name":"Giant Caterpillar","tags":["beast","melee"],"type":1},{"id":66,"name":"Giant Caterpillar","tags":["beast","melee"],"type":1},{"id":67,"name":"Giant Caterpillar","tags":["beast","melee"],"type":1},{"id":89,"name":"Giant Centipede","tags":["beast","boss","melee"],"type":2,"damageModifier":2.5,"healthModifier":50},{"id":46,"name":"Giant Rat","tags":["beast","melee"],"type":1},{"id":47,"name":"Giant Rat","tags":["beast","melee"],"type":1},{"id":48,"name":"Giant Rat","tags":["beast","melee"],"type":1},{"id":925,"name":"Spider Hatchlings","tags":["melee","beast"],"type":1},{"id":927,"name":"Spider Hatchlings","tags":["melee","beast"],"type":1},{"id":271,"name":"Skull-Face Spider","tags":["beast","boss","melee"],"type":2,"damageModifier":2.5,"healthModifier":50},{"id":69,"name":"Shadow","tags":["undead","melee","flying"],"type":1},{"id":70,"name":"Shadow","tags":["undead","melee","flying"],"type":1},{"id":71,"name":"Shadow","tags":["undead","melee","flying"],"type":1},{"id":1864,"name":"Wigged Giant Rat","tags":["melee","beast"],"type":1},{"id":1865,"name":"Wigged Giant Rat","tags":["melee","beast"],"type":1},{"id":1866,"name":"Wigged Giant Rat","tags":["melee","beast"],"type":1},{"id":1448,"name":"Shadow Demon","tags":["boss","fiend","demon","melee","flying"],"type":2,"damageModifier":2.5,"healthModifier":50},{"id":122,"name":"Goblin","tags":["goblin","humanoid","goblinoid","melee"],"type":1},{"id":123,"name":"Goblin","tags":["goblin","humanoid","goblinoid","melee"],"type":1},{"id":124,"name":"Goblin","tags":["goblin","humanoid","goblinoid","melee"],"type":1},{"id":428,"name":"Batiri Goblin","tags":["goblin","humanoid","goblinoid","melee"],"type":1},{"id":429,"name":"Batiri Goblin","tags":["goblin","humanoid","goblinoid","melee"],"type":1},{"id":430,"name":"Batiri Goblin","tags":["goblin","melee","goblinoid","humanoid"],"type":1},{"id":1053,"name":"Goblin","tags":["humanoid","goblinoid","ranged"],"type":1},{"id":1052,"name":"Goblin","tags":["humanoid","goblinoid","ranged"],"type":1},{"id":1051,"name":"Goblin","tags":["humanoid","goblinoid","ranged"],"type":1},{"id":1093,"name":"Goblin Gardener","tags":["boss","humanoid","goblinoid","goblin","melee"],"type":2,"damageModifier":2.5,"healthModifier":50},{"id":1622,"name":"Awakened Toadstool","tags":["melee","plant"],"type":1},{"id":1621,"name":"Awakened Toadstool","tags":["melee","plant"],"type":1},{"id":1620,"name":"Awakened Toadstool","tags":["melee","plant"],"type":1},{"id":1634,"name":"Awakened Shrub","tags":["melee","plant"],"type":1},{"id":1633,"name":"Awakened Shrub","tags":["melee","plant"],"type":1},{"id":1632,"name":"Awakened Shrub","tags":["melee","plant"],"type":1},{"id":148,"name":"Awakened Object","tags":["construct","melee"],"type":1},{"id":149,"name":"Awakened Object","tags":["construct","melee"],"type":1},{"id":150,"name":"Awakened Object","tags":["construct","melee"],"type":1},{"id":184,"name":"Awakened Object","tags":["construct","melee"],"type":1},{"id":829,"name":"Animated Armor","tags":["boss","construct","melee"],"type":2,"damageModifier":2.5,"healthModifier":50},{"id":1854,"name":"Motherhorn Thespian","tags":["melee","humanoid"],"type":1},{"id":1855,"name":"Motherhorn Thespian","tags":["melee","humanoid"],"type":1},{"id":1856,"name":"Motherhorn Thespian","tags":["melee","humanoid"],"type":1},{"id":1752,"name":"Scary Nesting Doll","tags":["boss","melee","construct","hits_based"],"type":2,"damageModifier":2.5,"healthModifier":25},{"id":1769,"name":"Darkling","tags":["fey","melee","darkling"],"type":1},{"id":1770,"name":"Darkling","tags":["fey","melee","darkling"],"type":1},{"id":1771,"name":"Darkling","tags":["fey","melee","darkling"],"type":1},{"id":1082,"name":"Pink Elephant","tags":["beast","melee"],"type":1},{"id":1081,"name":"Pink Elephant","tags":["beast","melee"],"type":1},{"id":1488,"name":"Illusory Fancy Red Panda","tags":["beast","melee"],"type":1},{"id":1489,"name":"Illusory Fancy Red Panda","tags":["beast","melee"],"type":1},{"id":1490,"name":"Illusory Fancy Red Panda","tags":["beast","melee"],"type":1},{"id":1558,"name":"Baeloth's King of Feathers","tags":["hits_based","boss","beast","ranged"],"type":2,"damageModifier":2.5,"healthModifier":50},{"id":61,"name":"Crawling Claw","tags":["melee","undead"],"type":1},{"id":62,"name":"Crawling Claw","tags":["undead","melee"],"type":1},{"id":63,"name":"Crawling Claw","tags":["undead","melee"],"type":1},{"id":255,"name":"Vampire Spawn","tags":["undead","melee"],"type":1},{"id":256,"name":"Vampire Spawn","tags":["undead","melee"],"type":1},{"id":257,"name":"Vampire Spawn","tags":["undead","melee"],"type":1},{"id":80,"name":"Zombie Villager","tags":["undead","melee"],"type":1,"damageModifier":1.25},{"id":81,"name":"Zombie Villager","tags":["undead","melee"],"type":1,"damageModifier":1.25},{"id":82,"name":"Zombie Villager","tags":["undead","melee"],"type":1,"damageModifier":1.25},{"id":242,"name":"Skeleton","tags":["undead","melee"],"type":1},{"id":243,"name":"Skeleton","tags":["undead","melee"],"type":1},{"id":244,"name":"Skeleton","tags":["undead","melee"],"type":1},{"id":231,"name":"Skeleton Archer","tags":["undead","ranged"],"type":1},{"id":232,"name":"Skeleton Archer","tags":["undead","ranged"],"type":1},{"id":233,"name":"Skeleton Archer","tags":["undead","ranged"],"type":1},{"id":176,"name":"Werewolf","tags":["humanoid","melee","lycanthrope"],"type":1},{"id":177,"name":"Werewolf","tags":["humanoid","melee","lycanthrope"],"type":1},{"id":178,"name":"Werewolf","tags":["humanoid","melee","lycanthrope"],"type":1},{"id":162,"name":"Dashing Werewolf","tags":["humanoid","melee","boss","lycanthrope"],"type":2,"damageModifier":2.5,"healthModifier":50},{"id":1857,"name":"Bullywug Korred","tags":["melee","fey","bullywug"],"type":1},{"id":1858,"name":"Bullywug Korred","tags":["melee","fey","bullywug"],"type":1},{"id":1859,"name":"Bullywug Korred","tags":["melee","fey","bullywug"],"type":1},{"id":1860,"name":"Bullywug Brigganock","tags":["melee","fey","bullywug"],"type":1},{"id":1861,"name":"Bullywug Brigganock","tags":["melee","fey","bullywug"],"type":1},{"id":1862,"name":"Bullywug Brigganock","tags":["melee","fey","bullywug"],"type":1},{"id":1614,"name":"Bullywug Riding a Crocodile","tags":["humanoid","bullywug","melee","boss","beast"],"type":2,"damageModifier":2.5,"healthModifier":50},{"id":946,"name":"Wedding Guest","tags":["humanoid","human"],"type":1},{"id":947,"name":"Wedding Guest","tags":["humanoid","human"],"type":1},{"id":948,"name":"Wedding Guest","tags":["humanoid","human"],"type":1},{"id":949,"name":"Wedding Guest","tags":["humanoid","human","ranged"],"type":1},{"id":950,"name":"Wedding Guest","tags":["humanoid","human","ranged"],"type":1},{"id":951,"name":"Wedding Guest","tags":["humanoid","human","ranged"],"type":1},{"id":73,"name":"Satyr","tags":["fey","melee"],"type":1},{"id":75,"name":"Satyr","tags":["fey","melee"],"type":1},{"id":1863,"name":"Thespian Yorven","tags":["boss","melee","humanoid","harengon","armor_based"],"type":2,"damageModifier":2.5,"healthModifier":50}],"quests":[{"id":8726,"type":2,"goal":25,"desc":"Enemies"},{"id":8727,"type":2,"goal":25,"desc":"Enemies"},{"id":8728,"type":1,"goal":25,"desc":"Gems"},{"id":8729,"type":2,"goal":25,"desc":"Enemies"},{"id":8730,"type":3,"goal":1,"desc":"Giant Centipede"},{"id":8731,"type":2,"goal":25,"desc":"Enemies"},{"id":8732,"type":2,"goal":25,"desc":"Enemies"},{"id":8733,"type":1,"goal":25,"desc":"Stage Decorations"},{"id":8734,"type":2,"goal":25,"desc":"Enemies"},{"id":8735,"type":3,"goal":1,"desc":"Skull-Face Spider"},{"id":8736,"type":2,"goal":25,"desc":"Enemies"},{"id":8737,"type":2,"goal":25,"desc":"Enemies"},{"id":8738,"type":1,"goal":25,"desc":"Paintbrushes"},{"id":8739,"type":2,"goal":25,"desc":"Enemies"},{"id":8740,"type":3,"goal":1,"desc":"Shadow Demon"},{"id":8741,"type":2,"goal":25,"desc":"Enemies"},{"id":8742,"type":2,"goal":25,"desc":"Enemies"},{"id":8743,"type":1,"goal":25,"desc":"Costumes"},{"id":8744,"type":2,"goal":25,"desc":"Enemies"},{"id":8745,"type":3,"goal":1,"desc":"Goblin Gardener"},{"id":8746,"type":2,"goal":25,"desc":"Enemies"},{"id":8747,"type":2,"goal":25,"desc":"Enemies"},{"id":8748,"type":1,"goal":25,"desc":"Prop Heads"},{"id":8749,"type":2,"goal":25,"desc":"Enemies"},{"id":8750,"type":3,"goal":1,"desc":"Animated Armor"},{"id":8751,"type":2,"goal":25,"desc":"Enemies"},{"id":8752,"type":2,"goal":25,"desc":"Enemies"},{"id":8753,"type":1,"goal":25,"desc":"Script Pages"},{"id":8754,"type":2,"goal":25,"desc":"Enemies"},{"id":8755,"type":3,"goal":1,"desc":"Scary Nesting Doll"},{"id":8756,"type":2,"goal":25,"desc":"Enemies"},{"id":8757,"type":2,"goal":25,"desc":"Enemies"},{"id":8758,"type":1,"goal":25,"desc":"Painted Gravestones"},{"id":8759,"type":2,"goal":25,"desc":"Enemies"},{"id":8760,"type":3,"goal":1,"desc":"Baeloth's King of Feathers"},{"id":8761,"type":2,"goal":25,"desc":"Enemies"},{"id":8762,"type":2,"goal":25,"desc":"Enemies"},{"id":8763,"type":1,"goal":25,"desc":"Skulls"},{"id":8764,"type":2,"goal":25,"desc":"Enemies"},{"id":8765,"type":3,"goal":1,"desc":"Dashing Werewolf"},{"id":8766,"type":2,"goal":25,"desc":"Enemies"},{"id":8767,"type":2,"goal":25,"desc":"Enemies"},{"id":8768,"type":1,"goal":25,"desc":"Rotting Salmon"},{"id":8769,"type":2,"goal":25,"desc":"Enemies"},{"id":8770,"type":3,"goal":1,"desc":"Bullywug Riding a Crocodile"},{"id":8771,"type":2,"goal":25,"desc":"Enemies"},{"id":8772,"type":2,"goal":25,"desc":"Enemies"},{"id":8773,"type":1,"goal":25,"desc":"Satyr Weapons"},{"id":8774,"type":2,"goal":25,"desc":"Enemies"},{"id":8775,"type":3,"goal":1,"desc":"Thespian Yorven"}],"distractions":[{"id":9,"name":"Bat (Flying)","isBush":false},{"id":13,"name":"Rat (Scurrying)","isBush":false},{"id":12,"name":"Bug (Scurrying)","isBush":false},{"id":18,"name":"Seagull (Flying)","isBush":false}]}