{"adventure":{"id":1627,"campaignId":31,"name":"A Cause for Kas","freeplay":1631,"locationId":87},"variants":[{"id":1628,"name":"Lend a Hand","requirements":{"ids":[1627]},"base":{"area":650,"rewards":[{"reward":"red_rubies","amount":1300}]},"patrons":[{"id":1,"area":750},{"id":2,"area":775},{"id":3,"area":800},{"id":4,"area":825},{"id":5,"area":950}]},{"id":1629,"name":"Deadly Dragons","requirements":{"ids":[1627]},"base":{"area":700,"rewards":[{"reward":"red_rubies","amount":1400}]},"patrons":[{"id":1,"area":800},{"id":2,"area":825},{"id":3,"area":850},{"id":4,"area":875},{"id":5,"area":1000}]}],"areas":[{"id":11316,"questId":11182,"bgId":1176,"monsters":[1520,1521,1522]},{"id":11317,"questId":11183,"bgId":1176,"monsters":[1540,1541,1542,148,149,150,184]},{"id":11318,"questId":11184,"bgId":1178,"monsters":[1540,1541,1542,1520,1521,1522]},{"id":11319,"questId":11185,"bgId":1178,"monsters":[148,149,150,184,1540,1541,1542]},{"id":11320,"questId":11186,"bgId":1178,"waves":[[1521,1521,1521,1522,1521],[1520,1520,1520,1522,1520],[42]]},{"id":11321,"questId":11187,"bgId":1114,"monsters":[2076,2077,2078,164,165,166]},{"id":11322,"questId":11188,"bgId":1114,"monsters":[719,720,721,2076,2077,2078]},{"id":11323,"questId":11189,"bgId":1114,"monsters":[719,720,721]},{"id":11324,"questId":11190,"bgId":1114,"monsters":[164,165,166,2076,2077,2078]},{"id":11325,"questId":11191,"bgId":1114,"waves":[[719,720,720,721,720],[721,721,721,720,721],[167]]},{"id":11326,"questId":11192,"bgId":1115,"monsters":[719,720,721,2076,2077,2078]},{"id":11327,"questId":11193,"bgId":1116,"monsters":[2076,2077,2078,1317,1318,1319]},{"id":11328,"questId":11194,"bgId":1115,"monsters":[1402,1403,1404]},{"id":11329,"questId":11195,"bgId":1118,"monsters":[1708,1709,1710,1703,1704,1705]},{"id":11330,"questId":11196,"bgId":1115,"waves":[[165,166,166,166,165],[164,165,164,164,164],[2079]]},{"id":11331,"questId":11197,"bgId":1112,"monsters":[205,206,207]},{"id":11332,"questId":11198,"bgId":1112,"monsters":[529,530,531,205,206,207]},{"id":11333,"questId":11199,"bgId":1112,"monsters":[567,568,569]},{"id":11334,"questId":11200,"bgId":1112,"monsters":[2076,2077,2078,205,206,207]},{"id":11335,"questId":11201,"bgId":1112,"waves":[[2077,2078,2077,2078,2077],[2077,2077,2076,2078,2078],[2082]]},{"id":11336,"questId":11202,"bgId":1108,"monsters":[2069,2070,2071]},{"id":11337,"questId":11203,"bgId":1108,"monsters":[2069,2070,2071,61,62,63]},{"id":11338,"questId":11204,"bgId":1108,"monsters":[2072,2073,2074]},{"id":11339,"questId":11205,"bgId":1108,"monsters":[2069,2070,2071,2072,2073,2074]},{"id":11340,"questId":11206,"bgId":1108,"waves":[[2072,2074,2074,2074,2073],[2072,2073,2073,2073,2074],[1663]]},{"id":11341,"questId":11207,"bgId":1104,"monsters":[894,895,896,2072,2073,2074]},{"id":11342,"questId":11208,"bgId":1104,"monsters":[80,81,82,2069,2070,2071]},{"id":11343,"questId":11209,"bgId":1104,"monsters":[80,81,82]},{"id":11344,"questId":11210,"bgId":1104,"monsters":[191,192,193,2072,2073,2074]},{"id":11345,"questId":11211,"bgId":1104,"waves":[[2071,2071,2071,2071,2071],[2071,2069,2070,2071,2071],[190]]},{"id":11346,"questId":11212,"bgId":1104,"monsters":[2118,2119,2120,2069,2070,2071]},{"id":11347,"questId":11213,"bgId":1104,"monsters":[2118,2119,2120,2072,2073,2074]},{"id":11348,"questId":11214,"bgId":1104,"monsters":[80,81,82]},{"id":11349,"questId":11215,"bgId":1104,"monsters":[2118,2119,2120,80,81,82]},{"id":11350,"questId":11216,"bgId":1104,"waves":[[2073,2073,2074,2073,2073],[2074,2074,2074,2072,2073],[466]]},{"id":11351,"questId":11217,"bgId":1111,"monsters":[2118,2119,2120,80,81,82]},{"id":11352,"questId":11218,"bgId":1111,"monsters":[2069,2070,2071,2072,2073,2074]},{"id":11353,"questId":11219,"bgId":1111,"monsters":[2118,2119,2120]},{"id":11354,"questId":11220,"bgId":1111,"monsters":[69,70,71,2072,2073,2074]},{"id":11355,"questId":11221,"bgId":1148,"waves":[[2072,2072,2072,2074,2074],[2074,2073,2073,2072,2074],[229]]},{"id":11356,"questId":11222,"bgId":1146,"monsters":[2114,2115,2116]},{"id":11357,"questId":11223,"bgId":1146,"monsters":[2114,2115,2116,2118,2119,2120]},{"id":11358,"questId":11224,"bgId":1146,"monsters":[2114,2115,2116]},{"id":11359,"questId":11225,"bgId":1146,"monsters":[2069,2070,2071,2114,2115,2116]},{"id":11360,"questId":11226,"bgId":1148,"waves":[[2120,2120,2119,2119,2118],[2119,2119,2118,2118,2120],[2117]]},{"id":11361,"questId":11227,"bgId":1147,"monsters":[2069,2070,2071,2072,2073,2074]},{"id":11362,"questId":11228,"bgId":1147,"monsters":[2069,2070,2071,2072,2073,2074]},{"id":11363,"questId":11229,"bgId":1147,"staticMonsters":[958],"monsters":[2118,2119,2120,2072,2073,2074]},{"id":11364,"questId":11230,"bgId":1213,"monsters":[69,70,71,1760,1761,1762]},{"id":11365,"questId":11231,"bgId":1213,"waves":[[255,256,257,255,256],[257,255,256,257,255],[2196]]}],"backgrounds":[{"id":1176,"distractions":[42,42],"isFixed":true},{"id":1178,"distractions":[42,42],"isFixed":true},{"id":1114,"distractions":[42,42]},{"id":1115,"distractions":[42,42]},{"id":1116,"distractions":[42,42],"isFixed":true},{"id":1118,"distractions":[42,42],"isFixed":true},{"id":1112,"distractions":[42,42]},{"id":1108,"distractions":[13,42,42],"tags":["underground"]},{"id":1104,"distractions":[42,42],"tags":["underground"],"isFixed":true},{"id":1111,"distractions":[9,13,42,14],"tags":["underground"]},{"id":1148,"distractions":[42,9],"tags":["underground"],"isFixed":true},{"id":1146,"distractions":[13,12,42],"tags":["underground"],"isFixed":true},{"id":1147,"distractions":[41,42],"tags":["underground"],"isFixed":true},{"id":1213,"distractions":[41,9],"tags":["underground"],"isFixed":true}],"monsters":[{"id":1520,"name":"Living Bigby's Hand","tags":["construct","melee","flying"],"type":1},{"id":1521,"name":"Living Bigby's Hand","tags":["construct","melee","flying"],"type":1},{"id":1522,"name":"Living Bigby's Hand","tags":["construct","melee","flying"],"type":1},{"id":1540,"name":"Acid Bubble","tags":["melee","construct"],"type":1},{"id":1541,"name":"Acid Bubble","tags":["melee","construct"],"type":1},{"id":1542,"name":"Acid Bubble","tags":["melee","construct"],"type":1},{"id":148,"name":"Awakened Object","tags":["construct","melee"],"type":1},{"id":149,"name":"Awakened Object","tags":["construct","melee"],"type":1},{"id":150,"name":"Awakened Object","tags":["construct","melee"],"type":1},{"id":184,"name":"Awakened Object","tags":["construct","melee"],"type":1},{"id":42,"name":"Fire Elemental","tags":["elemental","ranged","boss"],"type":2,"damageModifier":2.5,"healthModifier":50},{"id":2076,"name":"Cranium Rat Squeaker","tags":["aberration","melee"],"type":1},{"id":2077,"name":"Cranium Rat Squeaker","tags":["aberration","melee"],"type":1},{"id":2078,"name":"Cranium Rat Squeaker","tags":["aberration","melee"],"type":1},{"id":164,"name":"Wererat","tags":["humanoid","melee","lycanthrope"],"type":1},{"id":165,"name":"Wererat","tags":["humanoid","melee","lycanthrope"],"type":1},{"id":166,"name":"Wererat","tags":["humanoid","melee","lycanthrope"],"type":1},{"id":719,"name":"Zombie Rat","tags":["undead","melee"],"type":1},{"id":720,"name":"Zombie Rat","tags":["undead","melee"],"type":1},{"id":721,"name":"Zombie Rat","tags":["undead","melee"],"type":1},{"id":167,"name":"Wererat Leader","tags":["humanoid","melee","boss","lycanthrope"],"type":2,"damageModifier":2.5,"healthModifier":50},{"id":1317,"name":"Mimic Tavern Item","tags":["melee","monstrosity"],"type":1},{"id":1318,"name":"Mimic Tavern Item","tags":["melee","monstrosity"],"type":1},{"id":1319,"name":"Mimic Tavern Item","tags":["melee","monstrosity"],"type":1},{"id":1402,"name":"Kuo-toa Fighter","tags":["humanoid","melee","kuo-toa"],"type":1},{"id":1403,"name":"Kuo-toa Fighter","tags":["humanoid","melee","kuo-toa"],"type":1},{"id":1404,"name":"Kuo-toa Fighter","tags":["humanoid","melee","kuo-toa"],"type":1},{"id":1708,"name":"Minotaur","tags":["melee","monstrosity"],"type":1},{"id":1709,"name":"Minotaur","tags":["melee","monstrosity"],"type":1},{"id":1710,"name":"Minotaur","tags":["melee","monstrosity"],"type":1},{"id":1703,"name":"Drow Dagger Throwing Cultist","tags":["ranged","humanoid","elf","drow"],"type":1},{"id":1704,"name":"Drow Dagger Throwing Cultist","tags":["ranged","humanoid","elf","drow"],"type":1},{"id":1705,"name":"Drow Dagger Throwing Cultist","tags":["ranged","humanoid","elf","drow"],"type":1},{"id":2079,"name":"Giant Cranium Rat Squeaker","tags":["boss","aberration","melee"],"type":2,"damageModifier":2.5,"healthModifier":50},{"id":205,"name":"Bandit Wizard","tags":["bandit","ranged","human","humanoid"],"type":1},{"id":206,"name":"Bandit Wizard","tags":["bandit","human","humanoid","ranged"],"type":1},{"id":207,"name":"Bandit Wizard","tags":["human","humanoid","ranged","bandit"],"type":1},{"id":529,"name":"Yuan-ti Malison","tags":["yuan-ti","monstrosity","melee"],"type":1},{"id":530,"name":"Yuan-ti Malison","tags":["monstrosity","yuan-ti","melee"],"type":1},{"id":531,"name":"Yuan-ti Malison","tags":["monstrosity","melee","yuan-ti"],"type":1},{"id":567,"name":"Intellect Devourer","tags":["aberration","melee"],"type":1},{"id":568,"name":"Intellect Devourer","tags":["aberration","melee"],"type":1},{"id":569,"name":"Intellect Devourer","tags":["aberration","melee"],"type":1},{"id":2082,"name":"Sigil Ratcatcher","tags":["boss","humanoid","gith","melee"],"type":2,"damageModifier":2.5,"healthModifier":50},{"id":2069,"name":"Heralds of Dust Remnant","tags":["humanoid","melee","tiefling","planescape"],"type":1},{"id":2070,"name":"Heralds of Dust Remnant","tags":["humanoid","melee","half-elf","planescape"],"type":1},{"id":2071,"name":"Heralds of Dust Remnant","tags":["humanoid","melee","genasi","planescape"],"type":1},{"id":61,"name":"Crawling Claw","tags":["melee","undead"],"type":1},{"id":62,"name":"Crawling Claw","tags":["undead","melee"],"type":1},{"id":63,"name":"Crawling Claw","tags":["undead","melee"],"type":1},{"id":2072,"name":"Heralds of Dust Remnant","tags":["humanoid","ranged","tiefling","planescape"],"type":1},{"id":2073,"name":"Heralds of Dust Remnant","tags":["humanoid","ranged","half-elf","planescape"],"type":1},{"id":2074,"name":"Heralds of Dust Remnant","tags":["humanoid","ranged","genasi","planescape"],"type":1},{"id":1663,"name":"Undead Beholder","tags":["boss","armor_based","melee","ranged","undead"],"type":2,"damageModifier":2.5,"healthModifier":40},{"id":894,"name":"Flameskull","tags":["undead","ranged","flying"],"type":1},{"id":895,"name":"Flameskull","tags":["undead","ranged","flying"],"type":1},{"id":896,"name":"Flameskull","tags":["undead","ranged","flying"],"type":1},{"id":80,"name":"Zombie Villager","tags":["undead","melee"],"type":1,"damageModifier":1.25},{"id":81,"name":"Zombie Villager","tags":["undead","melee"],"type":1,"damageModifier":1.25},{"id":82,"name":"Zombie Villager","tags":["undead","melee"],"type":1,"damageModifier":1.25},{"id":191,"name":"Ghoul","tags":["undead","melee"],"type":1},{"id":192,"name":"Ghoul","tags":["undead","melee"],"type":1},{"id":193,"name":"Ghoul","tags":["undead","melee"],"type":1},{"id":190,"name":"Zombie Wizard","tags":["undead","ranged","boss"],"type":2,"damageModifier":2.5,"healthModifier":50},{"id":2118,"name":"Heralds of Dust Exorcist","tags":["humanoid","ranged","half-orc"],"type":1},{"id":2119,"name":"Heralds of Dust Exorcist","tags":["humanoid","human","ranged"],"type":1},{"id":2120,"name":"Heralds of Dust Exorcist","tags":["humanoid","human","ranged"],"type":1},{"id":466,"name":"Flesh Golem","tags":["construct","boss","melee"],"type":2,"damageModifier":2,"healthModifier":50},{"id":69,"name":"Shadow","tags":["undead","melee","flying"],"type":1},{"id":70,"name":"Shadow","tags":["undead","melee","flying"],"type":1},{"id":71,"name":"Shadow","tags":["undead","melee","flying"],"type":1},{"id":229,"name":"Ghast","tags":["undead","melee","boss"],"type":2,"damageModifier":2.5,"healthModifier":50},{"id":2114,"name":"Small Animated Coffin","tags":["construct","melee"],"type":1},{"id":2115,"name":"Small Animated Coffin","tags":["construct","melee"],"type":1},{"id":2116,"name":"Small Animated Coffin","tags":["construct","melee"],"type":1},{"id":2117,"name":"Animated Coffin","tags":["construct","melee","boss","armor_based"],"type":2,"healthModifier":50},{"id":958,"name":"Magical Barrier","tags":["static","hits_based"],"type":1,"damageModifier":0,"healthModifier":30},{"id":1760,"name":"Goblin Shadow","tags":["undead","melee"],"type":1},{"id":1761,"name":"Goblin Shadow","tags":["undead","melee"],"type":1},{"id":1762,"name":"Goblin Shadow","tags":["undead","melee"],"type":1},{"id":255,"name":"Vampire Spawn","tags":["undead","melee","vampire"],"type":1},{"id":256,"name":"Vampire Spawn","tags":["undead","melee","vampire"],"type":1},{"id":257,"name":"Vampire Spawn","tags":["undead","melee","vampire"],"type":1},{"id":2196,"name":"Dark Kas","tags":["boss","undead","melee","armor_based","vampire"],"type":2,"damageModifier":2.5,"healthModifier":50}],"quests":[{"id":11182,"type":2,"goal":25,"desc":"Enemies"},{"id":11183,"type":2,"goal":25,"desc":"Enemies"},{"id":11184,"type":1,"goal":25,"desc":"Spellbooks"},{"id":11185,"type":2,"goal":25,"desc":"Enemies"},{"id":11186,"type":3,"goal":1,"desc":"Fire Elemental"},{"id":11187,"type":2,"goal":25,"desc":"Enemies"},{"id":11188,"type":2,"goal":25,"desc":"Enemies"},{"id":11189,"type":1,"goal":25,"desc":"Zombie Rat Tails"},{"id":11190,"type":2,"goal":25,"desc":"Enemies"},{"id":11191,"type":3,"goal":1,"desc":"Wererat Leader"},{"id":11192,"type":2,"goal":25,"desc":"Enemies"},{"id":11193,"type":2,"goal":25,"desc":"Enemies"},{"id":11194,"type":1,"goal":25,"desc":"Fish"},{"id":11195,"type":2,"goal":25,"desc":"Enemies"},{"id":11196,"type":3,"goal":1,"desc":"Giant Cranium Rat Squeaker"},{"id":11197,"type":2,"goal":25,"desc":"Enemies"},{"id":11198,"type":2,"goal":25,"desc":"Enemies"},{"id":11199,"type":1,"goal":25,"desc":"Brains"},{"id":11200,"type":2,"goal":25,"desc":"Enemies"},{"id":11201,"type":3,"goal":1,"desc":"Sigil Rat Catcher"},{"id":11202,"type":2,"goal":25,"desc":"Enemies"},{"id":11203,"type":2,"goal":25,"desc":"Enemies"},{"id":11204,"type":1,"goal":25,"desc":"Heralds of Dust Signets"},{"id":11205,"type":2,"goal":25,"desc":"Enemies"},{"id":11206,"type":3,"goal":1,"desc":"Undead Beholder"},{"id":11207,"type":2,"goal":25,"desc":"Enemies"},{"id":11208,"type":2,"goal":25,"desc":"Enemies"},{"id":11209,"type":1,"goal":25,"desc":"Hands"},{"id":11210,"type":2,"goal":25,"desc":"Enemies"},{"id":11211,"type":3,"goal":1,"desc":"Zombie Wizard"},{"id":11212,"type":2,"goal":25,"desc":"Enemies"},{"id":11213,"type":2,"goal":25,"desc":"Enemies"},{"id":11214,"type":1,"goal":25,"desc":"Eyes"},{"id":11215,"type":2,"goal":25,"desc":"Enemies"},{"id":11216,"type":3,"goal":1,"desc":"Flesh Golem"},{"id":11217,"type":2,"goal":25,"desc":"Enemies"},{"id":11218,"type":2,"goal":25,"desc":"Enemies"},{"id":11219,"type":1,"goal":25,"desc":"Souls"},{"id":11220,"type":2,"goal":25,"desc":"Enemies"},{"id":11221,"type":3,"goal":1,"desc":"Ghast"},{"id":11222,"type":2,"goal":25,"desc":"Enemies"},{"id":11223,"type":2,"goal":25,"desc":"Enemies"},{"id":11224,"type":1,"goal":25,"desc":"Skulls"},{"id":11225,"type":2,"goal":25,"desc":"Enemies"},{"id":11226,"type":3,"goal":1,"desc":"Animated Coffin"},{"id":11227,"type":2,"goal":25,"desc":"Enemies"},{"id":11228,"type":2,"goal":25,"desc":"Enemies"},{"id":11229,"type":5,"goal":1,"desc":"Magical Barrier\t"},{"id":11230,"type":2,"goal":25,"desc":"Enemies"},{"id":11231,"type":3,"goal":1,"desc":"Dark Kas"}],"distractions":[{"id":42,"name":"Cranium Rat","isBush":false},{"id":13,"name":"Rat (Scurrying)","isBush":false},{"id":9,"name":"Bat (Flying)","isBush":false},{"id":14,"name":"Spider Drop","isBush":false},{"id":12,"name":"Bug (Scurrying)","isBush":false},{"id":41,"name":"Alien Bug","isBush":false}]}