{"adventure":{"id":1395,"campaignId":28,"name":"The Hunt for The Last Breath","freeplay":1399,"locationId":74},"variants":[{"id":1396,"name":"The Chaotic Hunt for The Last Breath","requirements":{"ids":[1395]},"base":{"area":750,"rewards":[{"reward":"red_rubies","amount":1500}]},"patrons":[{"id":1,"area":850},{"id":2,"area":875},{"id":3,"area":900},{"id":4,"area":925},{"id":5,"area":1050}]},{"id":1397,"name":"The Arcane Hunt for the Last Breath","requirements":{"ids":[1395],"count":{"count":34,"campaign":28}},"base":{"area":800,"rewards":[{"reward":"red_rubies","amount":1600}]},"patrons":[{"id":1,"area":900},{"id":2,"area":925},{"id":3,"area":950},{"id":4,"area":975},{"id":5,"area":1100}]}],"areas":[{"id":9816,"questId":9682,"bgId":1044,"monsters":[1921,1922,1923]},{"id":9817,"questId":9683,"bgId":1044,"monsters":[1796,1798,1797,1921,1922,1923]},{"id":9818,"questId":9684,"bgId":1044,"monsters":[1921,1922,1923]},{"id":9819,"questId":9685,"bgId":1044,"monsters":[1796,1798,1797,2004,2005,2006]},{"id":9820,"questId":9686,"bgId":1044,"waves":[[2005,2005,2005,2006,2005],[2004,2005,2004,2004,2005],[1799]]},{"id":9821,"questId":9687,"bgId":1045,"monsters":[2004,2005,2006]},{"id":9822,"questId":9688,"bgId":1045,"monsters":[1921,1922,1923,1796,1798,1797]},{"id":9823,"questId":9689,"bgId":1025,"monsters":[46,47,48]},{"id":9824,"questId":9690,"bgId":1045,"monsters":[1910,1911,1912]},{"id":9825,"questId":9691,"bgId":1045,"waves":[[1797,1798,1797,1798,1798],[1797,1798,1796,1798,1798],[2009]]},{"id":9826,"questId":9692,"bgId":1026,"monsters":[1796,1798,1797]},{"id":9827,"questId":9693,"bgId":1026,"monsters":[1910,1911,1912,1796,1798,1797]},{"id":9828,"questId":9694,"bgId":1027,"monsters":[1833,1834,1835]},{"id":9829,"questId":9695,"bgId":1027,"monsters":[1833,1834,1835,2004,2005,2006]},{"id":9830,"questId":9696,"bgId":1027,"waves":[[2006,2004,2004,2006,2006],[2004,2005,2006,2004,2006],[1826]]},{"id":9831,"questId":9697,"bgId":902,"monsters":[1822,1823,1824]},{"id":9832,"questId":9698,"bgId":902,"monsters":[1822,1823,1824,1678,1679,1680]},{"id":9833,"questId":9699,"bgId":902,"monsters":[1682,1683,1684]},{"id":9834,"questId":9700,"bgId":450,"monsters":[971,970,969]},{"id":9835,"questId":9701,"bgId":450,"waves":[[969,970,970,969,970],[971,971,970,969,971],[250]]},{"id":9836,"questId":9702,"bgId":450,"monsters":[2019,2020,2021,2022]},{"id":9837,"questId":9703,"bgId":450,"monsters":[972,968,967,2019,2020,2021,2022]},{"id":9838,"questId":9704,"bgId":452,"staticMonsters":[1934],"monsters":[972,968,967]},{"id":9839,"questId":9705,"bgId":452,"monsters":[971,970,969,1525,1526,1527]},{"id":9840,"questId":9706,"bgId":449,"waves":[[1525,1525,1525,1525,1527],[1526,1526,1526,1525,1526],[1524]]},{"id":9841,"questId":9707,"bgId":450,"monsters":[2019,2020,2021,2022]},{"id":9842,"questId":9708,"bgId":450,"monsters":[2019,2020,2021,2022,1525,1526,1527]},{"id":9843,"questId":9709,"bgId":450,"monsters":[1827,1828,1829]},{"id":9844,"questId":9710,"bgId":450,"monsters":[2019,2020,2021,2022,1827,1828,1829]},{"id":9845,"questId":9711,"bgId":449,"waves":[[2019,2020,2019,2019,2022],[2019,2020,2020,2021,2021],[1915]]},{"id":9846,"questId":9712,"bgId":452,"monsters":[971,970,969]},{"id":9847,"questId":9713,"bgId":452,"monsters":[971,970,969,972,968,967]},{"id":9848,"questId":9714,"bgId":452,"monsters":[972,968,967]},{"id":9849,"questId":9715,"bgId":453,"monsters":[971,970,969,972,968,967]},{"id":9850,"questId":9716,"bgId":453,"waves":[[968,972,972,972,967],[972,968,972,968,967],[1039]]},{"id":9851,"questId":9717,"bgId":1046,"monsters":[1921,1922,1923]},{"id":9852,"questId":9718,"bgId":1046,"monsters":[1921,1922,1923,780,781,782]},{"id":9853,"questId":9719,"bgId":1046,"monsters":[971,970,969,972,968,967]},{"id":9854,"questId":9720,"bgId":1047,"monsters":[971,970,969,780,781,782]},{"id":9855,"questId":9721,"bgId":1047,"waves":[[780,780,781,781,780],[782,781,780,781,780],[668]]},{"id":9856,"questId":9722,"bgId":1048,"monsters":[61,62,63]},{"id":9857,"questId":9723,"bgId":1048,"monsters":[61,62,63,719,720,721]},{"id":9858,"questId":9724,"bgId":1049,"monsters":[971,970,969]},{"id":9859,"questId":9725,"bgId":1049,"monsters":[971,970,969,972,968,967]},{"id":9860,"questId":9726,"bgId":1049,"waves":[[968,968,969,969,970],[968,968,967,967,970],[763]]},{"id":9861,"questId":9727,"bgId":1049,"monsters":[2004,2005,2006]},{"id":9862,"questId":9728,"bgId":1049,"monsters":[1921,1922,1923,1910,1911,1912]},{"id":9863,"questId":9729,"bgId":1049,"monsters":[2016,2017,2018]},{"id":9864,"questId":9730,"bgId":1050,"monsters":[2016,2017,2018,2004,2005,2006]},{"id":9865,"questId":9731,"bgId":1050,"staticMonsters":[2015],"waves":[[2016,2017,2016,2017,2016],[2017,2017,2018,2018,2016]]}],"backgrounds":[{"id":1044,"distractions":[32,32],"tags":["wildspace"],"isFixed":true},{"id":1045,"distractions":[32,32],"tags":["wildspace"],"isFixed":true},{"id":1025,"distractions":[12,12],"isFixed":true},{"id":1026,"distractions":[35,35],"tags":["wildspace"]},{"id":1027,"distractions":[31,35,31],"tags":["wildspace"],"isFixed":true},{"id":902,"distractions":[9,9],"tags":["underground"]},{"id":450,"distractions":[13,9],"tags":["underground"]},{"id":452,"distractions":[14,14],"tags":["underground"]},{"id":449,"distractions":[9],"isFixed":true},{"id":453,"distractions":[9],"tags":["underground"],"isFixed":true},{"id":1046,"distractions":[12,9],"isFixed":true},{"id":1047,"distractions":[13,12],"isFixed":true},{"id":1048,"distractions":[12,12],"isFixed":true},{"id":1049,"distractions":[]},{"id":1050,"distractions":[35,35],"tags":["wildspace"]}],"monsters":[{"id":1921,"name":"Space Mollymawk","tags":["beast","melee","flying"],"type":1},{"id":1922,"name":"Space Mollymawk","tags":["beast","melee","flying"],"type":1},{"id":1923,"name":"Space Mollymawk","tags":["beast","melee","flying"],"type":1},{"id":1796,"name":"Gray Scavver","tags":["monstrosity","melee","flying"],"type":1},{"id":1798,"name":"Gray Scavver","tags":["monstrosity","melee","flying"],"type":1},{"id":1797,"name":"Gray Scavver","tags":["monstrosity","melee","flying"],"type":1},{"id":2004,"name":"Small Eye Monger","tags":["melee","aberration","flying"],"type":1},{"id":2005,"name":"Small Eye Monger","tags":["melee","aberration","flying"],"type":1},{"id":2006,"name":"Small Eye Monger","tags":["melee","aberration","flying"],"type":1},{"id":1799,"name":"Night Scavver","tags":["boss","monstrosity","hits_based","melee","flying"],"type":2,"damageModifier":2.5,"healthModifier":50},{"id":46,"name":"Giant Rat","tags":["beast","melee"],"type":1},{"id":47,"name":"Giant Rat","tags":["beast","melee"],"type":1},{"id":48,"name":"Giant Rat","tags":["beast","melee"],"type":1},{"id":1910,"name":"Space Eel","tags":["beast","melee","flying"],"type":1},{"id":1911,"name":"Space Eel","tags":["beast","melee","flying"],"type":1},{"id":1912,"name":"Space Eel","tags":["beast","melee","flying"],"type":1},{"id":2009,"name":"Swarm of Space Eels","tags":["boss","melee","beast","flying"],"type":2,"damageModifier":2.5,"healthModifier":50},{"id":1833,"name":"Space Swine","tags":["beast","melee","flying"],"type":1},{"id":1834,"name":"Space Swine","tags":["beast","melee","flying"],"type":1},{"id":1835,"name":"Space Swine","tags":["beast","melee","flying"],"type":1},{"id":1826,"name":"Eye Monger","tags":["boss","aberration","melee","armor_based","flying"],"type":2,"damageModifier":2.5,"healthModifier":50},{"id":1822,"name":"Psurlon","tags":["aberration","melee"],"type":1},{"id":1823,"name":"Psurlon","tags":["aberration","melee"],"type":1},{"id":1824,"name":"Psurlon","tags":["aberration","melee"],"type":1},{"id":1678,"name":"Choker","tags":["melee","aberration"],"type":1},{"id":1679,"name":"Choker","tags":["melee","aberration"],"type":1},{"id":1680,"name":"Choker","tags":["melee","aberration"],"type":1},{"id":1682,"name":"Darkmantle","tags":["melee","monstrosity","flying"],"type":1},{"id":1683,"name":"Darkmantle","tags":["melee","monstrosity","flying"],"type":1},{"id":1684,"name":"Darkmantle","tags":["melee","monstrosity","flying"],"type":1},{"id":971,"name":"Xanathar Fighter","tags":["gnome","humanoid","xanathar","melee"],"type":1},{"id":970,"name":"Xanathar Fighter","tags":["dwarf","humanoid","xanathar","melee"],"type":1},{"id":969,"name":"Xanathar Fighter","tags":["gnome","humanoid","xanathar","melee"],"type":1},{"id":250,"name":"Poison-Spitting Spider","tags":["beast","ranged","boss"],"type":2,"damageModifier":2.5,"healthModifier":50},{"id":2019,"name":"Space Clown (melee)","tags":["fiend","melee"],"type":1},{"id":2020,"name":"Space Clown (melee)","tags":["fiend","melee"],"type":1},{"id":2021,"name":"Space Clown (melee)","tags":["fiend","melee"],"type":1},{"id":2022,"name":"Space Clown (melee)","tags":["fiend","melee"],"type":1},{"id":972,"name":"Xanathar Fighter","tags":["half-orc","xanathar","ranged","humanoid"],"type":1},{"id":968,"name":"Xanathar Fighter","tags":["gnome","humanoid","xanathar","ranged"],"type":1},{"id":967,"name":"Xanathar Fighter","tags":["dwarf","humanoid","xanathar","ranged"],"type":1},{"id":1934,"name":"Ship Debris","tags":["static","hits_based"],"type":1,"healthModifier":25},{"id":1525,"name":"Clown Gazer","tags":["ranged","aberration","flying"],"type":1},{"id":1526,"name":"Clown Gazer","tags":["ranged","aberration","flying"],"type":1},{"id":1527,"name":"Clown Gazer","tags":["ranged","aberration","flying"],"type":1},{"id":1524,"name":"Xanathar Clown","tags":["boss","aberration","armor_based","ranged","flying"],"type":2,"damageModifier":2.5,"healthModifier":50},{"id":1827,"name":"Space Clown","tags":["fiend","ranged"],"type":1},{"id":1828,"name":"Space Clown","tags":["fiend","ranged"],"type":1},{"id":1829,"name":"Space Clown","tags":["fiend","ranged"],"type":1},{"id":1915,"name":"Space Clown Ringmaster","tags":["boss","fiend","melee"],"type":2,"damageModifier":2.5,"healthModifier":50},{"id":1039,"name":"The Xanathar","tags":["boss","aberration","armor_based","ranged","flying"],"type":2,"damageModifier":2.5,"healthModifier":50},{"id":780,"name":"Gazer","tags":["ranged","aberration","flying"],"type":1},{"id":781,"name":"Gazer","tags":["ranged","aberration","flying"],"type":1},{"id":782,"name":"Gazer","tags":["ranged","aberration","flying"],"type":1},{"id":668,"name":"Xanathar Commander","tags":["xanathar","boss","humanoid","dwarf","melee"],"type":2,"damageModifier":2.5,"healthModifier":50},{"id":61,"name":"Crawling Claw","tags":["melee","undead"],"type":1},{"id":62,"name":"Crawling Claw","tags":["undead","melee"],"type":1},{"id":63,"name":"Crawling Claw","tags":["undead","melee"],"type":1},{"id":719,"name":"Zombie Rat","tags":["undead","melee"],"type":1},{"id":720,"name":"Zombie Rat","tags":["undead","melee"],"type":1},{"id":721,"name":"Zombie Rat","tags":["undead","melee"],"type":1},{"id":763,"name":"Barovian Bandit Leader","tags":["humanoid","human","bandit","boss","ranged"],"type":2,"damageModifier":2.5,"healthModifier":50},{"id":2016,"name":"Lunar Dragon Wyrmling","tags":["dragon","melee","flying"],"type":1},{"id":2017,"name":"Lunar Dragon Wyrmling","tags":["dragon","melee","flying"],"type":1},{"id":2018,"name":"Lunar Dragon Wyrmling","tags":["dragon","melee","flying"],"type":1},{"id":2015,"name":"Lunar Dragon","tags":["boss","dragon","armor_based","melee","ranged"],"type":2,"damageModifier":2.5,"healthModifier":50}],"quests":[{"id":9682,"type":2,"goal":25,"desc":"Enemies"},{"id":9683,"type":2,"goal":25,"desc":"Enemies"},{"id":9684,"type":1,"goal":25,"desc":"Feathers"},{"id":9685,"type":2,"goal":25,"desc":"Enemies"},{"id":9686,"type":3,"goal":1,"desc":"Night Scavver"},{"id":9687,"type":2,"goal":25,"desc":"Enemies"},{"id":9688,"type":2,"goal":25,"desc":"Enemies"},{"id":9689,"type":1,"goal":25,"desc":"Rat Tails"},{"id":9690,"type":2,"goal":25,"desc":"Enemies"},{"id":9691,"type":3,"goal":1,"desc":"Swarm of Space Eels"},{"id":9692,"type":2,"goal":25,"desc":"Enemies"},{"id":9693,"type":2,"goal":25,"desc":"Enemies"},{"id":9694,"type":1,"goal":25,"desc":"Space Swine Armor"},{"id":9695,"type":2,"goal":25,"desc":"Enemies"},{"id":9696,"type":3,"goal":1,"desc":"Eye Monger"},{"id":9697,"type":2,"goal":25,"desc":"Enemies"},{"id":9698,"type":2,"goal":25,"desc":"Enemies"},{"id":9699,"type":1,"goal":25,"desc":"Eyes"},{"id":9700,"type":2,"goal":25,"desc":"Enemies"},{"id":9701,"type":3,"goal":1,"desc":"Poison-Spitting Spider"},{"id":9702,"type":2,"goal":25,"desc":"Enemies"},{"id":9703,"type":2,"goal":25,"desc":"Enemies"},{"id":9704,"type":5,"goal":1,"desc":"Ship Debris"},{"id":9705,"type":2,"goal":25,"desc":"Enemies"},{"id":9706,"type":3,"goal":1,"desc":"Xanathar Clown"},{"id":9707,"type":2,"goal":25,"desc":"Enemies"},{"id":9708,"type":2,"goal":25,"desc":"Enemies"},{"id":9709,"type":1,"goal":25,"desc":"Ray Guns"},{"id":9710,"type":2,"goal":25,"desc":"Enemies"},{"id":9711,"type":3,"goal":1,"desc":"Space Clown Ringmaster"},{"id":9712,"type":2,"goal":25,"desc":"Enemies"},{"id":9713,"type":2,"goal":25,"desc":"Enemies"},{"id":9714,"type":1,"goal":25,"desc":"Xanathar Insignias"},{"id":9715,"type":2,"goal":25,"desc":"Enemies"},{"id":9716,"type":3,"goal":1,"desc":"Xanathar"},{"id":9717,"type":2,"goal":25,"desc":"Enemies"},{"id":9718,"type":2,"goal":25,"desc":"Enemies"},{"id":9719,"type":1,"goal":25,"desc":"Ropes"},{"id":9720,"type":2,"goal":25,"desc":"Enemies"},{"id":9721,"type":3,"goal":1,"desc":"Xanathar Commander"},{"id":9722,"type":2,"goal":25,"desc":"Enemies"},{"id":9723,"type":2,"goal":25,"desc":"Enemies"},{"id":9724,"type":1,"goal":25,"desc":"Swords"},{"id":9725,"type":2,"goal":25,"desc":"Enemies"},{"id":9726,"type":3,"goal":1,"desc":"Xanathar Troublemaker"},{"id":9727,"type":2,"goal":25,"desc":"Enemies"},{"id":9728,"type":2,"goal":25,"desc":"Enemies"},{"id":9729,"type":1,"goal":25,"desc":"Coins"},{"id":9730,"type":2,"goal":25,"desc":"Enemies"},{"id":9731,"type":3,"goal":1,"desc":"Lunar Dragon"}],"distractions":[{"id":32,"name":"Space Mollymawk","isBush":false},{"id":12,"name":"Bug (Scurrying)","isBush":false},{"id":35,"name":"Chwinga riding a space guppy","isBush":false},{"id":31,"name":"Space Guppy","isBush":false},{"id":9,"name":"Bat (Flying)","isBush":false},{"id":13,"name":"Rat (Scurrying)","isBush":false},{"id":14,"name":"Spider Drop","isBush":false}]}